PlasmidPoolAnalysis-0.1.0.data/scripts/pps
ppsAnalysis/__init__.py
ppsAnalysis/__main__.py
ppsAnalysis/alignment.py
ppsAnalysis/analysis.py
ppsAnalysis/cluster.py
ppsAnalysis/conf.py
ppsAnalysis/get_humangeneCDS.py
ppsAnalysis/human_main.py
ppsAnalysis/human_variant_analysis.py
ppsAnalysis/logthis.py
ppsAnalysis/main.py
ppsAnalysis/make_ref.py
ppsAnalysis/plot.py
ppsAnalysis/plot_main.py
ppsAnalysis/post_analysis.py
ppsAnalysis/pre_process_all_sequence.py
ppsAnalysis/process_input.py
ppsAnalysis/sge.py
ppsAnalysis/submit.py
ppsAnalysis/sup.py
ppsAnalysis/variant_call.py
ppsAnalysis/variants_analysis.py
ppsAnalysis/vcf_parser.py
ppsAnalysis/yeast_main.py
ppsAnalysis/yeast_variant_analysis.py
PlasmidPoolAnalysis-0.1.0.dist-info/METADATA
PlasmidPoolAnalysis-0.1.0.dist-info/WHEEL
PlasmidPoolAnalysis-0.1.0.dist-info/top_level.txt
PlasmidPoolAnalysis-0.1.0.dist-info/RECORD
