Metadata-Version: 2.1
Name: PlasmidPoolAnalysis
Version: 0.1.0
Summary: Analysis for plasmid pool sequencing data
Home-page: https://github.com/RyogaLi/PPS
Author: ROUJIA LI
Author-email: roujia.li@mail.utoronto.ca
License: UNKNOWN
Platform: UNKNOWN
Classifier: Development Status :: 3 - Alpha
Classifier: Intended Audience :: Developers
Classifier: Topic :: Software Development :: Build Tools
Classifier: License :: OSI Approved :: MIT License
Classifier: Programming Language :: Python :: 3.7
Requires-Python: >=3.7
Requires-Dist: pandas
Requires-Dist: seaborn
Requires-Dist: numpy
Requires-Dist: biopython
Requires-Dist: progressbar
